{
  "tags": [
    { "id": "all-products", "label": "All Products" },
    { "id": "hair-all", "label": "All Hair Types" },
    { "id": "hair-blonde", "label": "Blonde" },
    { "id": "hair-colour", "label": "Coloured Hair" },
    { "id": "hair-dry-damaged", "label": "Dry / Damaged" },
    { "id": "hair-frizz", "label": "Frizz Control" },
    { "id": "hair-curl", "label": "Wavy / Curly" },
    { "id": "hair-fine-volume", "label": "Fine / Volume" },
    { "id": "hair-fragile-loss", "label": "Fragile / Hair Loss" },
    { "id": "skin-all", "label": "Skin & Body" }
  ],
  "typeToTagIds": {
    "All hair types": ["all-products"],
    "All hair types (daily use)": ["all-products"],
    "Blonde hair": ["all-products", "hair-blonde"],
    "Coloured hair": ["all-products", "hair-colour"],
    "Dry or damaged hair": ["all-products", "hair-dry-damaged"],
    "Dry or dehydrated hair": ["all-products", "hair-dry-damaged"],
    "Long or damaged hair": ["all-products", "hair-dry-damaged"],
    "Very damaged hair": ["all-products", "hair-dry-damaged"],
    "Stressed or dull hair": ["all-products", "hair-dry-damaged", "hair-all"],
    "Active lifestyle hair": ["all-products", "hair-dry-damaged", "hair-all"],
    "Hair and scalp needing a break": ["all-products", "hair-all"],
    "Frizzy and unruly hair": ["all-products", "hair-frizz"],
    "Coarse or frizzy hair": ["all-products", "hair-frizz"],
    "Wavy or curly hair": ["all-products", "hair-curl"],
    "Wavy to very curly hair": ["all-products", "hair-curl"],
    "Fine or limp hair": ["all-products", "hair-fine-volume"],
    "Fine to medium hair": ["all-products", "hair-fine-volume"],
    "Fragile scalp and hair": ["all-products", "hair-fragile-loss"],
    "All skin types": ["all-products", "skin-all"]
  }
}